{"name":"build-javascript","namedChunkGroups":{"app":{"name":"app","assets":[{"name":"webpack-runtime-75271fec8d2dd65572e4.js","size":3705},{"name":"styles.68995fdb599eb8de28e0.css","size":129007},{"name":"framework-79da8e18abf8ceb9ec5a.js","size":140751},{"name":"app-e09b305a7e5639204bff.js","size":68543}],"filteredAssets":0,"assetsSize":342006,"filteredAuxiliaryAssets":5,"auxiliaryAssetsSize":635823},"component---src-pages-404-tsx":{"name":"component---src-pages-404-tsx","assets":[{"name":"component---src-pages-404-tsx-528f812eecc0f84d6ed1.js","size":756}],"filteredAssets":0,"assetsSize":756,"filteredAuxiliaryAssets":1,"auxiliaryAssetsSize":1894},"component---src-pages-index-tsx":{"name":"component---src-pages-index-tsx","assets":[{"name":"styles.68995fdb599eb8de28e0.css","size":129007},{"name":"98ea7ec2-78b8663558226ac4e47d.js","size":968},{"name":"1bfc9850-0199263e696598f981c3.js","size":1508},{"name":"d7eeaac4-2e9b4999ce235eda435c.js","size":971},{"name":"component---src-pages-index-tsx-515bb514df56400a75bb.js","size":12556}],"filteredAssets":0,"assetsSize":145010,"filteredAuxiliaryAssets":9,"auxiliaryAssetsSize":31821693}},"assetsByChunkName":{"app":["webpack-runtime-75271fec8d2dd65572e4.js","styles.68995fdb599eb8de28e0.css","framework-79da8e18abf8ceb9ec5a.js","app-e09b305a7e5639204bff.js"],"component---src-pages-404-tsx":["component---src-pages-404-tsx-528f812eecc0f84d6ed1.js"],"component---src-pages-index-tsx":["styles.68995fdb599eb8de28e0.css","98ea7ec2-78b8663558226ac4e47d.js","1bfc9850-0199263e696598f981c3.js","d7eeaac4-2e9b4999ce235eda435c.js","component---src-pages-index-tsx-515bb514df56400a75bb.js"]},"childAssetsByChunkName":{}}